[
  {
    "name": "海阔天空 (Live)",
    "singer": "Beyond",
    "album": "Beyond The Story Live 2005",
    "img": "https://p2.music.126.net/0a2NayHgHaf5WQTEYoHahg==/109951163972046213.jpg?param=177y177",
    "priority": "10"
  },
  {
    "name": "旧日的足迹",
    "singer": "Beyond",
    "album": "Control",
    "img": "https://p2.music.126.net/_hBhAUEbkSnW534QiqsRwQ==/109951166350502185.jpg?param=130y130"
  },
  {
    "name": "永远等待",
    "singer": "Beyond",
    "album": "再见理想",
    "img": "https://p1.music.126.net/drMMU_vv6DO9cp9TLnNXZQ==/109951164811209703.jpg?param=130y130"
  },
  {
    "name": "海阔天空",
    "singer": "Beyond",
    "album": "Beyond 25th Anniversary",
    "img": "https://p2.music.126.net/zZtUDuWk6qIe3ezMt4UMjg==/109951165796417308.jpg?param=130y130",
    "priority": "top"
  },
  {
    "name": "光辉岁月",
    "singer": "Beyond",
    "album": "Beyond 25th Anniversary",
    "img": "https://p2.music.126.net/zZtUDuWk6qIe3ezMt4UMjg==/109951165796417308.jpg?param=130y130"
  },
  {
    "name": "农民",
    "singer": "Beyond",
    "album": "Beyond 20th Anniversary",
    "img": "https://p2.music.126.net/oauvOyQDA4HICYAL8rc4fQ==/588238720882448.jpg?param=130y130"
  },
  {
    "name": "灰色轨迹",
    "singer": "Beyond",
    "album": "Beyond 25th Anniversary",
    "img": "https://p2.music.126.net/zZtUDuWk6qIe3ezMt4UMjg==/109951165796417308.jpg?param=130y130"
  },
  {
    "name": "冷雨夜",
    "singer": "Beyond",
    "album": "Beyond 25th Anniversary",
    "img": "https://p2.music.126.net/zZtUDuWk6qIe3ezMt4UMjg==/109951165796417308.jpg?param=130y130"
  },
  {
    "name": "喜欢你",
    "singer": "Beyond",
    "album": "Beyond 25th Anniversary",
    "img": "https://p2.music.126.net/zZtUDuWk6qIe3ezMt4UMjg==/109951165796417308.jpg?param=130y130"
  },
  {
    "name": "真的爱你",
    "singer": "Beyond",
    "album": "Beyond 25th Anniversary",
    "img": "https://p2.music.126.net/zZtUDuWk6qIe3ezMt4UMjg==/109951165796417308.jpg?param=130y130"
  },
  {
    "name": "不再犹豫",
    "singer": "Beyond",
    "album": "Beyond 25th Anniversary",
    "img": "https://p2.music.126.net/zZtUDuWk6qIe3ezMt4UMjg==/109951165796417308.jpg?param=130y130"
  },
  {
    "name": "We Don't Wanna Make It Without You",
    "singer": "Beyond",
    "album": "二楼后座",
    "img": "https://p2.music.126.net/7pcI2vWoWjgCYkCZ_oFQkw==/109951168914746924.jpg?param=130y130"
  },
  {
    "name": "遥远的 Paradise",
    "singer": "Beyond",
    "album": "二楼后座",
    "img": "https://p2.music.126.net/7pcI2vWoWjgCYkCZ_oFQkw==/109951168914746924.jpg?param=130y130"
  },
  {
    "name": "祝您愉快",
    "singer": "Beyond",
    "album": "二楼后座",
    "img": "https://p2.music.126.net/7pcI2vWoWjgCYkCZ_oFQkw==/109951168914746924.jpg?param=130y130",
    "priority": "top"
  },
  {
    "name": "Amani",
    "singer": "Beyond",
    "album": "The Ultimate Story",
    "img": "https://p2.music.126.net/h5XXOuri1-E-OtpE2L-4sg==/1781208837010258.jpg?param=130y130"
  },
  {
    "name": "走不开的快乐",
    "singer": "Beyond",
    "album": "乐与怒",
    "img": "https://p2.music.126.net/cDSBOHwJ2066X50xMJH59Q==/109951169217321420.jpg?param=130y130"
  },
  {
    "name": "大地",
    "singer": "Beyond",
    "album": "秘密警察",
    "img": "https://p2.music.126.net/p4n4HOTS14aeeJ2xfTGUeQ==/109951170517224188.jpg?param=130y130"
  },
  {
    "name": "岁月如歌",
    "singer": "陈奕迅",
    "album": "Live For Today",
    "img": "https://p2.music.126.net/c9G5m3D3GQxqbTt6MqJIgw==/18956679974612526.jpg?param=130y130"
  },
  {
    "name": "Shall We Talk",
    "singer": "陈奕迅",
    "album": "Shall We Dance? Shall We Talk!",
    "img": "https://p2.music.126.net/jr5XGr69K4k_U1eBnL-JYw==/109951170241860133.jpg?param=130y130"
  }
]